dictlearn/__init__.py
dictlearn/_dictionary_learning.py
dictlearn/_utils.py
dictlearn/kernel_approximation.py
dictlearn/kernels.py
dictlearn/datasets/__init__.py
dictlearn/datasets/arface.py
dictlearn/datasets/caltech101.py
dictlearn/datasets/mnist.py
dictlearn/datasets/yaleb.py
dictlearn/methods/__init__.py
dictlearn/methods/_aksvd.py
dictlearn/methods/_atom.py
dictlearn/methods/_ksvd.py
dictlearn/methods/_mod.py
dictlearn/methods/_nsgk.py
dictlearn/methods/_odl.py
dictlearn/methods/_omp.py
dictlearn/methods/_sgk.py
dictlearn/methods/_uaksvd.py
dictlearn/models/DDL.py
dictlearn/models/DPL.py
dictlearn/models/KDDL.py
dictlearn/models/KDPL.py
dictlearn/models/KLCDL.py
dictlearn/models/LCDL.py
dictlearn/models/__init__.py
dictlearn/utils/__init__.py
dictlearn/utils/data_utils.py
dictlearn/utils/generic_utils.py
dictlearn-0.2.2.dist-info/LICENSE
dictlearn-0.2.2.dist-info/METADATA
dictlearn-0.2.2.dist-info/WHEEL
dictlearn-0.2.2.dist-info/top_level.txt
dictlearn-0.2.2.dist-info/RECORD
