Metadata-Version: 2.1
Name: dictlearn
Version: 0.2.2
Summary: Dictionary Learning Toolbox
Home-page: https://gitlab.com/unibuc/graphomaly/dictionary-learning
Author: Paul Irofti, Denis Ilie-Ablachim, Bogdan Dumitrescu
Author-email: graphomaly@fmi.unibuc.ro
Project-URL: Bug Tracker, https://gitlab.com/unibuc/graphomaly/dictionary-learning/-/issues
Keywords: dictionary learning,sparse representations,machine learning,signal processing
Classifier: Programming Language :: Python :: 3
Classifier: License :: OSI Approved :: BSD License
Classifier: Operating System :: OS Independent
Requires-Python: >=3.6
License-File: LICENSE
Requires-Dist: numpy
Requires-Dist: scipy
